pymeteobridgedata/__init__.py
pymeteobridgedata/api.py
pymeteobridgedata/const.py
pymeteobridgedata/conversion.py
pymeteobridgedata/data.py
pymeteobridgedata/exceptions.py
pymeteobridgedata-0.1.21.dist-info/licenses/LICENSE
pymeteobridgedata-0.1.21.dist-info/METADATA
pymeteobridgedata-0.1.21.dist-info/WHEEL
pymeteobridgedata-0.1.21.dist-info/top_level.txt
pymeteobridgedata-0.1.21.dist-info/RECORD
