Metadata-Version: 2.4
Name: pymeteobridgedata
Version: 0.1.21
Summary: Python Wrapper to communicate with a Meteobridge Weather Data Logger
Home-page: https://github.com/briis/pymeteobridge
Author: Bjarne Riis
Author-email: bjarne@briis.com
License: MIT
Keywords: Meteobridge,Weather,pws,personal-weather-station Python
Classifier: Development Status :: 4 - Beta
Classifier: Intended Audience :: Developers
Classifier: Topic :: Software Development :: Build Tools
Classifier: License :: OSI Approved :: MIT License
Classifier: Programming Language :: Python :: 3.8
Classifier: Programming Language :: Python :: 3.9
Classifier: Programming Language :: Python :: 3.10
License-File: LICENSE
Requires-Dist: aiohttp
Requires-Dist: python-aqi
Provides-Extra: dev
Requires-Dist: base36; extra == "dev"
Requires-Dist: black; extra == "dev"
Requires-Dist: build; extra == "dev"
Requires-Dist: coverage[toml]; extra == "dev"
Requires-Dist: flake8; extra == "dev"
Requires-Dist: flake8-docstrings; extra == "dev"
Requires-Dist: ipython; extra == "dev"
Requires-Dist: mypy; extra == "dev"
Requires-Dist: pip-tools; extra == "dev"
Requires-Dist: pydocstyle; extra == "dev"
Requires-Dist: pylint; extra == "dev"
Requires-Dist: pylint_strict_informational; extra == "dev"
Requires-Dist: pyproject-flake8; extra == "dev"
Requires-Dist: pytest; extra == "dev"
Requires-Dist: pytest-asyncio; extra == "dev"
Requires-Dist: pytest-cov; extra == "dev"
Requires-Dist: pytest-sugar; extra == "dev"
Requires-Dist: pytest-timeout>=1.2.1; extra == "dev"
Requires-Dist: termcolor; extra == "dev"
Requires-Dist: tox; extra == "dev"
Requires-Dist: types-pillow; extra == "dev"
Requires-Dist: types-pytz; extra == "dev"
Requires-Dist: types-termcolor; extra == "dev"
Provides-Extra: shell
Requires-Dist: ipython; extra == "shell"
Requires-Dist: termcolor; extra == "shell"
Dynamic: license-file
